geetest_solver/__init__.py
geetest_solver/async_wrapper.py
geetest_solver/best.pt
geetest_solver/hybrid_solver.py
geetest_solver/iconcrush_solver.py
geetest_solver/solver.py
geetest_solver-1.0.9.dist-info/LICENSE
geetest_solver-1.0.9.dist-info/METADATA
geetest_solver-1.0.9.dist-info/WHEEL
geetest_solver-1.0.9.dist-info/top_level.txt
geetest_solver-1.0.9.dist-info/RECORD
