Metadata-Version: 2.1
Name: geetest-solver
Version: 1.0.9
Summary: GeeTest v4 ICON CAPTCHA solver using YOLO + template matching
Home-page: https://github.com/syncrain/geetest-solver
Author: kv
License: UNKNOWN
Platform: UNKNOWN
Requires-Python: >=3.8
License-File: LICENSE
Requires-Dist: requests>=2.31.0
Requires-Dist: ultralytics>=8.0.0
Requires-Dist: opencv-python>=4.8.0
Requires-Dist: pillow>=10.0.0
Requires-Dist: numpy>=1.24.0
Requires-Dist: pycryptodome>=3.19.0
Requires-Dist: scipy>=1.11.0
Requires-Dist: scikit-image>=0.21.0
Provides-Extra: interactive
Requires-Dist: matplotlib>=3.7.0; extra == "interactive"
